[{"Estado":"0","email":"javier.perez1314@gmail.com","mensaje":"asasdasd"},{"Estado":"0","email":"javier.perez1314@gmail.com","mensaje":"asasdasd"},{"Estado":"0","email":"javier.perez1314@gmail.com","mensaje":"asasdasd"},{"Estado":"0","email":"javier.perez1314@gmail.com","mensaje":"asasdasd"},{"Estado":"0","email":"javier.perez1314@gmail.com","mensaje":"asasdasd"},{"Estado":"0","email":"javier.perez26@outlook.comda.asd","mensaje":"asdasd"},{"Estado":"0","email":"javier.perez1314@gmail.com","mensaje":"asdasd"},{"Estado":"0","email":"javier.perez1314@gmail.com","mensaje":"asdasd"},{"Estado":"0","email":"javier.perez26@outlook.com","mensaje":"asdasd"},{"Estado":"0","email":"javier.perez26@outlook.com","mensaje":"asdasd"},{"Estado":"0","email":"javier.perez26@outlook.com","mensaje":"sasdfgsdgfsf"},{"Estado":"0","email":"javier.perez26@outlook.com","mensaje":"sasdfgsdgfsf"},{"Estado":"0","email":"javier.perez26@outlook.comasda","mensaje":"asdasdasd"},{"Estado":"0","email":"javier.perez26@outlook.comasda","mensaje":"asdasdasd"},{"Estado":"0","email":"javier.perez26@outlook.com","mensaje":"asdasd"}]